pandas_bj/__init__.py
pandas_bj/between.py
pandas_bj/between_merge.py
pandas_bj/custom_merge.py
pandas_bj-0.1.1.dist-info/METADATA
pandas_bj-0.1.1.dist-info/RECORD
pandas_bj-0.1.1.dist-info/WHEEL
pandas_bj-0.1.1.dist-info/top_level.txt
