Metadata-Version: 2.1
Name: pandas-bj
Version: 0.1.1
Summary: Pandas BJ (Between Join) provides efficient way to use `JOIN` and `BETWEEN` comparison. with pandas.DataFrame.
Home-page: https://github.com/archiba/pandas_bj
Author: Yuki Chiba
Author-email: yuki.music.0283@gmail.com
License: MIT
Platform: UNKNOWN
Classifier: Programming Language :: Python :: 3.6
Requires-Dist: nose (>=1.3.7)
Requires-Dist: numpy (>=1.14.0)
Requires-Dist: pandas (>=0.22.0)
